dash_fullcalendar/FullCalendar.py
dash_fullcalendar/__init__.py
dash_fullcalendar/_imports_.py
dash_fullcalendar/dash_fullcalendar.min.js
dash_fullcalendar/dash_fullcalendar.min.js.map
dash_fullcalendar/metadata.json
dash_fullcalendar/package-info.json
dash_fullcalendar-0.1.3.dist-info/licenses/LICENSE
dash_fullcalendar-0.1.3.dist-info/METADATA
dash_fullcalendar-0.1.3.dist-info/WHEEL
dash_fullcalendar-0.1.3.dist-info/top_level.txt
dash_fullcalendar-0.1.3.dist-info/RECORD
