Metadata-Version: 2.4
Name: dash_fullcalendar
Version: 0.1.3
Summary: A Plotly Dash wrapper for FullCalendar
Author: Scott Kilgore <skilgore@landmarktx.com>
License: MIT
Classifier: Framework :: Dash
License-File: LICENSE
Dynamic: author
Dynamic: classifier
Dynamic: description
Dynamic: description-content-type
Dynamic: license
Dynamic: license-file
Dynamic: summary
